odoo9_addon_website_sale_require_login-9.0.1.0.0.99.dev2-py2.7-nspkg.pth
odoo_addons/website_sale_require_login/__openerp__.py
odoo_addons/website_sale_require_login/__init__.py
odoo_addons/website_sale_require_login/README.rst
odoo_addons/website_sale_require_login/i18n/it.po
odoo_addons/website_sale_require_login/i18n/sl.po
odoo_addons/website_sale_require_login/views/website_sale.xml
odoo_addons/website_sale_require_login/views/assets.xml
odoo_addons/website_sale_require_login/controllers/main.py
odoo_addons/website_sale_require_login/controllers/__init__.py
odoo_addons/website_sale_require_login/static/description/icon.png
odoo_addons/website_sale_require_login/static/src/js/website_sale_tour_buy_login.tour.js
odoo9_addon_website_sale_require_login-9.0.1.0.0.99.dev2.dist-info/top_level.txt
odoo9_addon_website_sale_require_login-9.0.1.0.0.99.dev2.dist-info/WHEEL
odoo9_addon_website_sale_require_login-9.0.1.0.0.99.dev2.dist-info/RECORD
odoo9_addon_website_sale_require_login-9.0.1.0.0.99.dev2.dist-info/metadata.json
odoo9_addon_website_sale_require_login-9.0.1.0.0.99.dev2.dist-info/DESCRIPTION.rst
odoo9_addon_website_sale_require_login-9.0.1.0.0.99.dev2.dist-info/METADATA
odoo9_addon_website_sale_require_login-9.0.1.0.0.99.dev2.dist-info/namespace_packages.txt
